apache_ariatosca-0.2.0.dist-info/DESCRIPTION.rst
apache_ariatosca-0.2.0.dist-info/METADATA
apache_ariatosca-0.2.0.dist-info/RECORD
apache_ariatosca-0.2.0.dist-info/WHEEL
apache_ariatosca-0.2.0.dist-info/entry_points.txt
apache_ariatosca-0.2.0.dist-info/metadata.json
apache_ariatosca-0.2.0.dist-info/top_level.txt
aria/__init__.py
aria/core.py
aria/exceptions.py
aria/extension.py
aria/logger.py
aria/cli/__init__.py
aria/cli/ascii_art.py
aria/cli/color.py
aria/cli/csar.py
aria/cli/defaults.py
aria/cli/env.py
aria/cli/exceptions.py
aria/cli/execution_logging.py
aria/cli/helptexts.py
aria/cli/inputs.py
aria/cli/logger.py
aria/cli/main.py
aria/cli/service_template_utils.py
aria/cli/table.py
aria/cli/utils.py
aria/cli/commands/__init__.py
aria/cli/commands/executions.py
aria/cli/commands/logs.py
aria/cli/commands/node_templates.py
aria/cli/commands/nodes.py
aria/cli/commands/plugins.py
aria/cli/commands/reset.py
aria/cli/commands/service_templates.py
aria/cli/commands/services.py
aria/cli/commands/workflows.py
aria/cli/config/__init__.py
aria/cli/config/config.py
aria/cli/config/config_template.yaml
aria/cli/core/__init__.py
aria/cli/core/aria.py
aria/modeling/__init__.py
aria/modeling/constraints.py
aria/modeling/exceptions.py
aria/modeling/functions.py
aria/modeling/mixins.py
aria/modeling/models.py
aria/modeling/orchestration.py
aria/modeling/relationship.py
aria/modeling/service_changes.py
aria/modeling/service_common.py
aria/modeling/service_instance.py
aria/modeling/service_template.py
aria/modeling/types.py
aria/modeling/utils.py
aria/orchestrator/__init__.py
aria/orchestrator/decorators.py
aria/orchestrator/events.py
aria/orchestrator/exceptions.py
aria/orchestrator/execution_preparer.py
aria/orchestrator/plugin.py
aria/orchestrator/context/__init__.py
aria/orchestrator/context/common.py
aria/orchestrator/context/exceptions.py
aria/orchestrator/context/operation.py
aria/orchestrator/context/toolbelt.py
aria/orchestrator/context/workflow.py
aria/orchestrator/execution_plugin/__init__.py
aria/orchestrator/execution_plugin/common.py
aria/orchestrator/execution_plugin/constants.py
aria/orchestrator/execution_plugin/environment_globals.py
aria/orchestrator/execution_plugin/exceptions.py
