Metadata-Version: 2.0
Name: apache-ariatosca
Version: 0.2.0
Summary: ARIA
Home-page: http://ariatosca.incubator.apache.org/
Author: ARIA
Author-email: dev@ariatosca.incubator.apache.org
License: Apache License 2.0
Download-URL: https://dist.apache.org/repos/dist/release/incubator/ariatosca/0.2.0-incubating
Platform: any
Classifier: Development Status :: 4 - Beta
Classifier: Environment :: Console
Classifier: Environment :: Web Environment
Classifier: Intended Audience :: Developers
Classifier: Intended Audience :: System Administrators
Classifier: License :: OSI Approved :: Apache Software License
Classifier: Operating System :: OS Independent
Classifier: Programming Language :: Python
Classifier: Programming Language :: Python :: 2
Classifier: Programming Language :: Python :: 2.7
Classifier: Topic :: Software Development :: Libraries :: Python Modules
Classifier: Topic :: System :: Networking
Classifier: Topic :: System :: Systems Administration
Requires-Dist: CacheControl[filecache] (<0.13,>=0.11.0)
Requires-Dist: Jinja2 (<3.0,>=2.9)
Requires-Dist: PrettyTable (>=0.7,<0.8)
Requires-Dist: SQLAlchemy (<1.2,>=1.1)
Requires-Dist: backports.shutil-get-terminal-size (>=1,<2)
Requires-Dist: blinker (<1.5,>=1.4)
Requires-Dist: bottle (<0.13,>=0.12)
Requires-Dist: click (<7,>=6)
Requires-Dist: click-didyoumean (>=0.0.3,<0.1)
Requires-Dist: colorama (>=0.3,<=0.4)
Requires-Dist: jsonpickle (<=1.0,>=0.9)
Requires-Dist: logutils (>=0.3,<0.4)
Requires-Dist: networkx (<2.1,>=2.0)
Requires-Dist: psutil (>=5.4,<5.5)
Requires-Dist: requests (>=2.3,<2.14)
Requires-Dist: retrying (>=1.3,<1.4)
Requires-Dist: ruamel.yaml (>=0.15,<0.16)
Requires-Dist: shortuuid (>=0.5,<0.6)
Requires-Dist: wagon (<0.7,>=0.6)
Provides-Extra: ssh
Requires-Dist: Fabric (>=1.14,<1.15); extra == 'ssh'
Provides-Extra: ssh
Requires-Dist: pypiwin32 (>=220); sys_platform=="win32" and extra == 'ssh'
